bibtexpy/__init__.py
bibtexpy/grammar.py
bibtexpy/models.py
bibtexpy-0.0.1.dist-info/LICENSE
bibtexpy-0.0.1.dist-info/METADATA
bibtexpy-0.0.1.dist-info/WHEEL
bibtexpy-0.0.1.dist-info/top_level.txt
bibtexpy-0.0.1.dist-info/RECORD
