Metadata-Version: 2.1
Name: bibtexpy
Version: 0.0.1
Summary: Python bibtex parser and serializer.
Home-page: https://github.com/coreofscience/bibtexpy
Author: Oscar David Arbeláez Echeverri
Author-email: odarbelaeze@gmail.com
License: MIT license
Keywords: bibtext,parser
Platform: UNKNOWN
Classifier: Development Status :: 1 - Planning
Classifier: Intended Audience :: Developers
Classifier: Intended Audience :: Education
Classifier: License :: OSI Approved :: MIT License
Classifier: Natural Language :: English
Classifier: Programming Language :: Python :: 3
Classifier: Programming Language :: Python :: 3.7
Classifier: Programming Language :: Python :: 3.8
Classifier: Programming Language :: Python :: 3.9
Requires-Python: >=3.6
Requires-Dist: pyparsing (>=2.4.7<3)
